Files/__init__.py
Files/pyg_btn.py
pyg_btn-0.0.1.dist-info/METADATA
pyg_btn-0.0.1.dist-info/WHEEL
pyg_btn-0.0.1.dist-info/top_level.txt
pyg_btn-0.0.1.dist-info/RECORD
