Metadata-Version: 2.1
Name: pyg-btn
Version: 0.0.1
Summary: Make buttons in pygame with pyg_btn!
Home-page: UNKNOWN
Author: SATAN01 (Shourya sinha)
Author-email: <shouryasinha001@gmail.com>
License: UNKNOWN
Keywords: python,pygame,buttons,game-development
Platform: UNKNOWN
Classifier: Development Status :: 1 - Planning
Classifier: Intended Audience :: Developers
Classifier: Programming Language :: Python :: 3
Classifier: Operating System :: Unix
Classifier: Operating System :: MacOS :: MacOS X
Classifier: Operating System :: Microsoft :: Windows
Requires-Dist: pygame
